datagenkit/__init__.py
datagenkit/augmentation_pipeline.py
datagenkit/neural_style_transfer.py
datagenkit/patch_mixing.py
datagenkit/traditional_augmentations.py
datagenkit-0.1.dist-info/licenses/LICENSE
datagenkit-0.1.dist-info/METADATA
datagenkit-0.1.dist-info/WHEEL
datagenkit-0.1.dist-info/entry_points.txt
datagenkit-0.1.dist-info/top_level.txt
datagenkit-0.1.dist-info/RECORD
