Metadata-Version: 2.4
Name: datagenkit
Version: 0.1
Summary: A Python package for generating diverse and enriched image datasets using traditional, neural style transfer, and patch mixing augmentations.
Home-page: https://github.com/Jayavardhan-7/DataGenKit-
Author: Jayavardhan
Author-email: jayavardhanperala@gmail.com
Keywords: image augmentation,dataset generation,neural style transfer,cutmix,mixup,computer vision,deep learning
Classifier: Programming Language :: Python :: 3
Classifier: License :: OSI Approved :: MIT License
Classifier: Operating System :: OS Independent
Classifier: Topic :: Scientific/Engineering :: Image Processing
Classifier: Topic :: Scientific/Engineering :: Artificial Intelligence
Classifier: Development Status :: 3 - Alpha
Requires-Python: >=3.8
License-File: LICENSE
Requires-Dist: gradio
Requires-Dist: albumentations
Requires-Dist: torch
Requires-Dist: torchvision
Requires-Dist: scikit-image
Requires-Dist: numpy
Requires-Dist: opencv-python
Dynamic: author
Dynamic: author-email
Dynamic: classifier
Dynamic: description
Dynamic: description-content-type
Dynamic: home-page
Dynamic: keywords
Dynamic: license-file
Dynamic: requires-dist
Dynamic: requires-python
Dynamic: summary
